Workbook

Sheet Start Here
A1: Biweekly Paycheck Budget — Excel companion (SavingsPrintablesCo)
A3: This workbook has 5 sheets. You only ever type in two of them:
A4: 1. Bills Split — fill it once: every monthly bill, assigned to Paycheck 1 or 2. Totals per paycheck calculate themselves.
A5: 2. 26 Paychecks — your year log. One row per payday (26 rows). Type the date and the amounts; Total Out, Left and Running Savings calculate themselves, and the Month column fills itself from the date.
A6: 3. Year at a Glance — do not type here. It builds itself from the 26 Paychecks log (SUMIF by month): paychecks per month, income, bills, saved and left, plus year totals.
A7: 4. Paycheck Worksheet — the detailed category template for a single pay period. Duplicate this sheet whenever you want a detailed breakdown for one paycheck; the 26 Paychecks log stays your permanent record.
A8: Works in Microsoft Excel, Google Sheets and Apple Numbers. Personal use only. A budgeting tool, not financial advice.
A10: IF YOU USE GOOGLE SHEETS (FREE)
A11: The file you downloaded is already yours and editable — the copy step below is only so you always keep one clean original.
A12: 1. Upload biweekly_budget.xlsx to your Google Drive.
A13: 2. Open it with Google Sheets, then choose File > Make a copy.
A14: 3. Work in the copy. If the file opens as a read-only preview, you are still in the Drive preview — open it in Google Sheets first, then make the copy.
... A27: EXAMPLE — the first three pay periods are filled in so you can see the totals build themselves. Your copy starts blank.

Sheet 26 Paychecks
A1: 26 Paychecks — one row per payday, all year
A3: # | B3: Payday date | C3: Month # | D3: Income | E3: Bills | F3: Everyday spending | G3: Debt | H3: Savings | I3: Other | J3: Total out | K3: Left | L3: Running savings
A4: 1 | B4: 46024 | C4: =IF(B4="","",MONTH(B4)) | D4: 2100 | E4: 1150 | F4: 320 | G4: 150 | H4: 200 | I4: 40 | J4: =SUM(E4:I4) | K4: =D4-J4 | L4: =H4
A5: 2 | B5: 46038 | C5: =IF(B5="","",MONTH(B5)) | D5: 2137 | E5: 1175 | F5: 338 | G5: 150 | H5: 250 | I5: 40 | J5: =SUM(E5:I5) | K5: =D5-J5 | L5: =L4+H5
A6: 3 | B6: 46052 | C6: =IF(B6="","",MONTH(B6)) | D6: 2174 | E6: 1200 | F6: 356 | G6: 150 | H6: 200 | I6: 40 | J6: =SUM(E6:I6) | K6: =D6-J6 | L6: =L5+H6
A7: 4 | C7: =IF(B7="","",MONTH(B7)) | D7: 0 | E7: 0 | F7: 0 | G7: 0 | H7: 0 | I7: 0 | J7: =SUM(E7:I7) | K7: =D7-J7 | L7: =L6+H7
A8: 5 | C8: =IF(B8="","",MONTH(B8)) | D8: 0 | E8: 0 | F8: 0 | G8: 0 | H8: 0 | I8: 0 | J8: =SUM(E8:I8) | K8: =D8-J8 | L8: =L7+H8
A9: 6 | C9: =IF(B9="","",MONTH(B9)) | D9: 0 | E9: 0 | F9: 0 | G9: 0 | H9: 0 | I9: 0 | J9: =SUM(E9:I9) | K9: =D9-J9 | L9: =L8+H9
A10: 7 | C10: =IF(B10="","",MONTH(B10)) | D10: 0 | E10: 0 | F10: 0 | G10: 0 | H10: 0 | I10: 0 | J10: =SUM(E10:I10) | K10: =D10-J10 | L10: =L9+H10
A11: 8 | C11: =IF(B11="","",MONTH(B11)) | D11: 0 | E11: 0 | F11: 0 | G11: 0 | H11: 0 | I11: 0 | J11: =SUM(E11:I11) | K11: =D11-J11 | L11: =L10+H11
A12: 9 | C12: =IF(B12="","",MONTH(B12)) | D12: 0 | E12: 0 | F12: 0 | G12: 0 | H12: 0 | I12: 0 | J12: =SUM(E12:I12) | K12: =D12-J12 | L12: =L11+H12
A13: 10 | C13: =IF(B13="","",MONTH(B13)) | D13: 0 | E13: 0 | F13: 0 | G13: 0 | H13: 0 | I13: 0 | J13: =SUM(E13:I13) | K13: =D13-J13 | L13: =L12+H13
A14: 11 | C14: =IF(B14="","",MONTH(B14)) | D14: 0 | E14: 0 | F14: 0 | G14: 0 | H14: 0 | I14: 0 | J14: =SUM(E14:I14) | K14: =D14-J14 | L14: =L13+H14
A15: 12 | C15: =IF(B15="","",MONTH(B15)) | D15: 0 | E15: 0 | F15: 0 | G15: 0 | H15: 0 | I15: 0 | J15: =SUM(E15:I15) | K15: =D15-J15 | L15: =L14+H15
A16: 13 | C16: =IF(B16="","",MONTH(B16)) | D16: 0 | E16: 0 | F16: 0 | G16: 0 | H16: 0 | I16: 0 | J16: =SUM(E16:I16) | K16: =D16-J16 | L16: =L15+H16
A17: 14 | C17: =IF(B17="","",MONTH(B17)) | D17: 0 | E17: 0 | F17: 0 | G17: 0 | H17: 0 | I17: 0 | J17: =SUM(E17:I17) | K17: =D17-J17 | L17: =L16+H17
A18: 15 | C18: =IF(B18="","",MONTH(B18)) | D18: 0 | E18: 0 | F18: 0 | G18: 0 | H18: 0 | I18: 0 | J18: =SUM(E18:I18) | K18: =D18-J18 | L18: =L17+H18
... A29: 26 | C29: =IF(B29="","",MONTH(B29)) | D29: 0 | E29: 0 | F29: 0 | G29: 0 | H29: 0 | I29: 0 | J29: =SUM(E29:I29) | K29: =D29-J29 | L29: =L28+H29
A30: YEAR | D30: =SUM(D4:D29) | E30: =SUM(E4:E29) | F30: =SUM(F4:F29) | G30: =SUM(G4:G29) | H30: =SUM(H4:H29) | I30: =SUM(I4:I29) | J30: =SUM(J4:J29) | K30: =SUM(K4:K29) | L30: =L29

Sheet Paycheck Worksheet
A1: Paycheck Worksheet — detailed template for one pay period (duplicate this sheet as needed)
A2: Payday date:
A3: Paycheck income: | B3: 0
A5: Category | B5: Planned | C5: Actual
A6: Housing | B6: 0 | C6: 0
A7: Food & groceries | B7: 0 | C7: 0
A8: Transport | B8: 0 | C8: 0
A9: Bills & utilities | B9: 0 | C9: 0
A10: Debt payment | B10: 0 | C10: 0
A11: Savings | B11: 0 | C11: 0
A12: Fun & dining | B12: 0 | C12: 0
A13: Personal | B13: 0 | C13: 0
A14: Other | B14: 0 | C14: 0
A15: TOTAL | B15: =SUM(B6:B14) | C15: =SUM(C6:C14)
A16: Left to assign (planned) | B16: =$B$3-B15
A17: Left (actual) | B17: =$B$3-C15

Sheet Bills Split
A1: Bill Split — assign each monthly bill to Paycheck 1 or 2
A3: Bill | B3: Due date (day) | C3: Amount | D3: Paycheck (1 or 2)
A4: Rent (part 1 of 2) | B4: 1 | C4: 600 | D4: 1
A5: Electric | B5: 10 | C5: 145 | D5: 1
A6: Phone | B6: 12 | C6: 65 | D6: 1
A7: Internet | B7: 15 | C7: 60 | D7: 1
A8: Rent (part 2 of 2) | B8: 1 | C8: 600 | D8: 2
A9: Water | B9: 20 | C9: 55 | D9: 2
A10: Car insurance | B10: 22 | C10: 180 | D10: 2
A11: Streaming subscriptions | B11: 25 | C11: 35 | D11: 2
A12: Minimum debt payment | B12: 28 | C12: 210 | D12: 2
A22: Total for Paycheck 1: | C22: =SUMIF(D4:D20,1,C4:C20)
A23: Total for Paycheck 2: | C23: =SUMIF(D4:D20,2,C4:C20)

Sheet Year at a Glance
A1: Year at a Glance — builds itself from the 26 Paychecks log. Do not type here.
A3: Month | B3: Paychecks | C3: Income | D3: Bills | E3: Saved | F3: Left
A4: January | B4: =COUNTIF('26 Paychecks'!$C$4:$C$29,1) | C4: =SUMIF('26 Paychecks'!$C$4:$C$29,1,'26 Paychecks'!$D$4:$D$29) | D4: =SUMIF('26 Paychecks'!$C$4:$C$29,1,'26 Paychecks'!$E$4:$E$29) | E4: =SUMIF('26 Paychecks'!$C$4:$C$29,1,'26 Paychecks'!$H$4:$H$29) | F4: =SUMIF('26 Paychecks'!$C$4:$C$29,1,'26 Paychecks'!$K$4:$K$29)
A5: February | B5: =COUNTIF('26 Paychecks'!$C$4:$C$29,2) | C5: =SUMIF('26 Paychecks'!$C$4:$C$29,2,'26 Paychecks'!$D$4:$D$29) | D5: =SUMIF('26 Paychecks'!$C$4:$C$29,2,'26 Paychecks'!$E$4:$E$29) | E5: =SUMIF('26 Paychecks'!$C$4:$C$29,2,'26 Paychecks'!$H$4:$H$29) | F5: =SUMIF('26 Paychecks'!$C$4:$C$29,2,'26 Paychecks'!$K$4:$K$29)
A6: March | B6: =COUNTIF('26 Paychecks'!$C$4:$C$29,3) | C6: =SUMIF('26 Paychecks'!$C$4:$C$29,3,'26 Paychecks'!$D$4:$D$29) | D6: =SUMIF('26 Paychecks'!$C$4:$C$29,3,'26 Paychecks'!$E$4:$E$29) | E6: =SUMIF('26 Paychecks'!$C$4:$C$29,3,'26 Paychecks'!$H$4:$H$29) | F6: =SUMIF('26 Paychecks'!$C$4:$C$29,3,'26 Paychecks'!$K$4:$K$29)
A7: April | B7: =COUNTIF('26 Paychecks'!$C$4:$C$29,4) | C7: =SUMIF('26 Paychecks'!$C$4:$C$29,4,'26 Paychecks'!$D$4:$D$29) | D7: =SUMIF('26 Paychecks'!$C$4:$C$29,4,'26 Paychecks'!$E$4:$E$29) | E7: =SUMIF('26 Paychecks'!$C$4:$C$29,4,'26 Paychecks'!$H$4:$H$29) | F7: =SUMIF('26 Paychecks'!$C$4:$C$29,4,'26 Paychecks'!$K$4:$K$29)
A8: May | B8: =COUNTIF('26 Paychecks'!$C$4:$C$29,5) | C8: =SUMIF('26 Paychecks'!$C$4:$C$29,5,'26 Paychecks'!$D$4:$D$29) | D8: =SUMIF('26 Paychecks'!$C$4:$C$29,5,'26 Paychecks'!$E$4:$E$29) | E8: =SUMIF('26 Paychecks'!$C$4:$C$29,5,'26 Paychecks'!$H$4:$H$29) | F8: =SUMIF('26 Paychecks'!$C$4:$C$29,5,'26 Paychecks'!$K$4:$K$29)
A9: June | B9: =COUNTIF('26 Paychecks'!$C$4:$C$29,6) | C9: =SUMIF('26 Paychecks'!$C$4:$C$29,6,'26 Paychecks'!$D$4:$D$29) | D9: =SUMIF('26 Paychecks'!$C$4:$C$29,6,'26 Paychecks'!$E$4:$E$29) | E9: =SUMIF('26 Paychecks'!$C$4:$C$29,6,'26 Paychecks'!$H$4:$H$29) | F9: =SUMIF('26 Paychecks'!$C$4:$C$29,6,'26 Paychecks'!$K$4:$K$29)
A10: July | B10: =COUNTIF('26 Paychecks'!$C$4:$C$29,7) | C10: =SUMIF('26 Paychecks'!$C$4:$C$29,7,'26 Paychecks'!$D$4:$D$29) | D10: =SUMIF('26 Paychecks'!$C$4:$C$29,7,'26 Paychecks'!$E$4:$E$29) | E10: =SUMIF('26 Paychecks'!$C$4:$C$29,7,'26 Paychecks'!$H$4:$H$29) | F10: =SUMIF('26 Paychecks'!$C$4:$C$29,7,'26 Paychecks'!$K$4:$K$29)
A11: August | B11: =COUNTIF('26 Paychecks'!$C$4:$C$29,8) | C11: =SUMIF('26 Paychecks'!$C$4:$C$29,8,'26 Paychecks'!$D$4:$D$29) | D11: =SUMIF('26 Paychecks'!$C$4:$C$29,8,'26 Paychecks'!$E$4:$E$29) | E11: =SUMIF('26 Paychecks'!$C$4:$C$29,8,'26 Paychecks'!$H$4:$H$29) | F11: =SUMIF('26 Paychecks'!$C$4:$C$29,8,'26 Paychecks'!$K$4:$K$29)
A12: September | B12: =COUNTIF('26 Paychecks'!$C$4:$C$29,9) | C12: =SUMIF('26 Paychecks'!$C$4:$C$29,9,'26 Paychecks'!$D$4:$D$29) | D12: =SUMIF('26 Paychecks'!$C$4:$C$29,9,'26 Paychecks'!$E$4:$E$29) | E12: =SUMIF('26 Paychecks'!$C$4:$C$29,9,'26 Paychecks'!$H$4:$H$29) | F12: =SUMIF('26 Paychecks'!$C$4:$C$29,9,'26 Paychecks'!$K$4:$K$29)
A13: October | B13: =COUNTIF('26 Paychecks'!$C$4:$C$29,10) | C13: =SUMIF('26 Paychecks'!$C$4:$C$29,10,'26 Paychecks'!$D$4:$D$29) | D13: =SUMIF('26 Paychecks'!$C$4:$C$29,10,'26 Paychecks'!$E$4:$E$29) | E13: =SUMIF('26 Paychecks'!$C$4:$C$29,10,'26 Paychecks'!$H$4:$H$29) | F13: =SUMIF('26 Paychecks'!$C$4:$C$29,10,'26 Paychecks'!$K$4:$K$29)
A14: November | B14: =COUNTIF('26 Paychecks'!$C$4:$C$29,11) | C14: =SUMIF('26 Paychecks'!$C$4:$C$29,11,'26 Paychecks'!$D$4:$D$29) | D14: =SUMIF('26 Paychecks'!$C$4:$C$29,11,'26 Paychecks'!$E$4:$E$29) | E14: =SUMIF('26 Paychecks'!$C$4:$C$29,11,'26 Paychecks'!$H$4:$H$29) | F14: =SUMIF('26 Paychecks'!$C$4:$C$29,11,'26 Paychecks'!$K$4:$K$29)
A15: December | B15: =COUNTIF('26 Paychecks'!$C$4:$C$29,12) | C15: =SUMIF('26 Paychecks'!$C$4:$C$29,12,'26 Paychecks'!$D$4:$D$29) | D15: =SUMIF('26 Paychecks'!$C$4:$C$29,12,'26 Paychecks'!$E$4:$E$29) | E15: =SUMIF('26 Paychecks'!$C$4:$C$29,12,'26 Paychecks'!$H$4:$H$29) | F15: =SUMIF('26 Paychecks'!$C$4:$C$29,12,'26 Paychecks'!$K$4:$K$29)
A16: YEAR TOTAL | B16: =SUM(B4:B15) | C16: =SUM(C4:C15) | D16: =SUM(D4:D15) | E16: =SUM(E4:E15) | F16: =SUM(F4:F15)
